dagster_cloud_cli/__init__.py
dagster_cloud_cli/config_utils.py
dagster_cloud_cli/docker_utils.py
dagster_cloud_cli/entrypoint.py
dagster_cloud_cli/gql.py
dagster_cloud_cli/pex_utils.py
dagster_cloud_cli/py.typed
dagster_cloud_cli/types.py
dagster_cloud_cli/ui.py
dagster_cloud_cli/utils.py
dagster_cloud_cli/version.py
dagster_cloud_cli/commands/__init__.py
dagster_cloud_cli/commands/config.py
dagster_cloud_cli/commands/metrics.py
dagster_cloud_cli/commands/branch_deployment/__init__.py
dagster_cloud_cli/commands/ci/__init__.py
dagster_cloud_cli/commands/ci/checks.py
dagster_cloud_cli/commands/ci/report.py
dagster_cloud_cli/commands/ci/state.py
dagster_cloud_cli/commands/ci/utils.py
dagster_cloud_cli/commands/deployment/__init__.py
dagster_cloud_cli/commands/deployment/alert_policies/__init__.py
dagster_cloud_cli/commands/deployment/alert_policies/commands.py
dagster_cloud_cli/commands/integration/__init__.py
dagster_cloud_cli/commands/integration/atlan/__init__.py
dagster_cloud_cli/commands/job/__init__.py
dagster_cloud_cli/commands/organization/__init__.py
dagster_cloud_cli/commands/organization/saml/__init__.py
dagster_cloud_cli/commands/organization/saml/commands.py
dagster_cloud_cli/commands/run/__init__.py
dagster_cloud_cli/commands/serverless/Dockerfile
dagster_cloud_cli/commands/serverless/Dockerfile.dagster-cloud-cli
dagster_cloud_cli/commands/serverless/__init__.py
dagster_cloud_cli/commands/workspace/__init__.py
dagster_cloud_cli/config/__init__.py
dagster_cloud_cli/config/jinja_template_loader.py
dagster_cloud_cli/config/list_merge_strategies.py
dagster_cloud_cli/config/loader.py
dagster_cloud_cli/config/merger.py
dagster_cloud_cli/config/models.py
dagster_cloud_cli/core/__init__.py
dagster_cloud_cli/core/agent_queue.py
dagster_cloud_cli/core/alert_types.py
dagster_cloud_cli/core/artifacts.py
dagster_cloud_cli/core/docker_runner.py
dagster_cloud_cli/core/errors.py
dagster_cloud_cli/core/graphql_client.py
dagster_cloud_cli/core/workspace.py
dagster_cloud_cli-1.12.13.dist-info/licenses/LICENSE
dagster_cloud_cli-1.12.13.dist-info/METADATA
dagster_cloud_cli-1.12.13.dist-info/WHEEL
dagster_cloud_cli-1.12.13.dist-info/entry_points.txt
dagster_cloud_cli-1.12.13.dist-info/top_level.txt
dagster_cloud_cli-1.12.13.dist-info/RECORD
